[
  {
    "id": 1,
    "name": "sibikrishna",
    "title": "this is sibikrishna titile",
    "content": "Eiusmod aliqua velit ex ipsum asdfas. Irure culpa tempor tempor ea incididunt ullamco nisi officia elit occaecat elit quis mollit. Labore eiusmod sit eiusmod Lorem aliquip irure amet cillum. Laborum ex labore enim ea. Quis anim eu consectetur labore adipisicing culpa magna cualpa anim enim officia a\n"
  },
  {
    "id": 2,
    "name": "nigashini",
    "title": "how are you",
    "content": "what is the content for this is for nothing i guess"
  },
  {
    "id": 3,
    "name": "samyutha",
    "title": "drinking",
    "content": "water is not enough to drink there is something better than that, that is water"
  },
  {
    "id": 4,
    "name": "this is",
    "title": "this is title of the screen",
    "content": "asdfaf"
  },
  {
    "name": "kayal",
    "title": "how are you",
    "content": "lorem ipsum"
  },
  {
    "name": "how ",
    "title": "",
    "content": ""
  },
  {
    "name": "asfdad",
    "title": "asdfasdf",
    "content": "asdfasdf"
  },
  {
    "name": "aa",
    "title": "aa",
    "content": "aa"
  },
  {
    "name": "sibikrishna1",
    "title": "sibikrishna is a warrior",
    "content": "sibikrishna is a man who lived in the town called the great ponnirai"
  },
  {
    "name": "hello ",
    "title": "testing again for the side nav",
    "content": "how are you mate"
  },
  {
    "name": "not that",
    "title": "how do doing thambi nalla irukkingala",
    "content": "how are mate happy doing ahh"
  }
]